LogisticRegression/__init__.py
LogisticRegression/main.py
logistic_regression_from_scratch-2025.0.1.dist-info/METADATA
logistic_regression_from_scratch-2025.0.1.dist-info/WHEEL
logistic_regression_from_scratch-2025.0.1.dist-info/top_level.txt
logistic_regression_from_scratch-2025.0.1.dist-info/RECORD
