Metadata-Version: 2.4
Name: logistic_regression_from_scratch
Version: 2025.0.1
Requires-Python: >=3.9
Requires-Dist: numpy
Requires-Dist: pandas
